data_encode_tool-0.0.1.dist-info/METADATA
data_encode_tool-0.0.1.dist-info/WHEEL
data_encode_tool/__init__.py
data_encode_tool/data_encode_tool.cpython-39-x86_64-linux-gnu.so
data_encode_tool-0.0.1.dist-info/RECORD
